{
  "status": "ready",
  "originalFilePath": "videos/main-video.mp4",
  "provider": "vercel-blob",
  "providerMetadata": {
    "vercel-blob": {
      "key": "videos/main-video.mp4",
      "url": "https://1ugmug1q7fenqlgk.public.blob.vercel-storage.com/videos/main-video-qRdTv3gkTEhaXQfPnlwbG1msWwHfkv.mp4",
      "contentType": "video/mp4"
    }
  },
  "createdAt": 1774038621923,
  "updatedAt": 1774038624773,
  "size": 32348808,
  "sources": [
    {
      "src": "https://1ugmug1q7fenqlgk.public.blob.vercel-storage.com/videos/main-video-qRdTv3gkTEhaXQfPnlwbG1msWwHfkv.mp4",
      "type": "video/mp4"
    }
  ]
}
